rf_inferno/__init__.py
rf_inferno-0.0.1.dist-info/METADATA
rf_inferno-0.0.1.dist-info/WHEEL
rf_inferno-0.0.1.dist-info/top_level.txt
rf_inferno-0.0.1.dist-info/RECORD
