Metadata-Version: 2.4
Name: rf-inferno
Version: 0.0.1
Summary: Package name reservation
Home-page: https://github.com/rapidfireai
Author: RapidFire AI Inc.
Author-email: support@rapidfire.ai
Dynamic: author
Dynamic: author-email
Dynamic: description
Dynamic: description-content-type
Dynamic: home-page
Dynamic: summary
